mcp_weather_sse/_init_.py
mcp_weather_sse/_main_.py
mcp_weather_sse/server.py
mcp_get_system_info-0.1.0.dist-info/METADATA
mcp_get_system_info-0.1.0.dist-info/WHEEL
mcp_get_system_info-0.1.0.dist-info/entry_points.txt
mcp_get_system_info-0.1.0.dist-info/top_level.txt
mcp_get_system_info-0.1.0.dist-info/RECORD
