Metadata-Version: 2.4
Name: mcp-get-system-info
Version: 0.1.0
Summary: Add your description here
Requires-Python: >=3.12
Requires-Dist: mcp[cli]>=1.13.1
